django_keycloak/__init__.py
django_keycloak/admin.py
django_keycloak/api/__init__.py
django_keycloak/api/filters.py
django_keycloak/api/serializers.py
django_keycloak/api/urls.py
django_keycloak/api/views.py
django_keycloak/apps.py
django_keycloak/authentication.py
django_keycloak/backends.py
django_keycloak/config.py
django_keycloak/connector.py
django_keycloak/errors.py
django_keycloak/management/__init__.py
django_keycloak/management/commands/__init__.py
django_keycloak/management/commands/sync_keycloak_users.py
django_keycloak/managers.py
django_keycloak/middleware.py
django_keycloak/migrations/0001_initial.py
django_keycloak/migrations/0001_redo_migrations_0001to0005.py
django_keycloak/migrations/0002_auto_20210209_1503.py
django_keycloak/migrations/0003_auto_20210406_1426.py
django_keycloak/migrations/0004_keycloakuserautoid.py
django_keycloak/migrations/0005_auto_20211231_1702.py
django_keycloak/migrations/__init__.py
django_keycloak/mixins.py
django_keycloak/models.py
django_keycloak/tasks.py
django_keycloak/token.py
django_uw_keycloak-2.0.2.dist-info/LICENSE
django_uw_keycloak-2.0.2.dist-info/WHEEL
django_uw_keycloak-2.0.2.dist-info/METADATA
django_uw_keycloak-2.0.2.dist-info/RECORD
