Metadata-Version: 2.1
Name: django-uw-keycloak
Version: 2.0.2
Summary: Middleware to allow authorization using Keycloak and Django
Home-page: https://github.com/urbanplatform/django-keycloak-auth
License: MIT
Keywords: keycloak,django,authorization
Author: Ubiwhere
Author-email: urbanplatform@ubiwhere.com
Requires-Python: >=3.7,<4
Classifier: Environment :: Web Environment
Classifier: Framework :: Django
Classifier: Intended Audience :: Developers
Classifier: License :: OSI Approved :: MIT License
Classifier: Programming Language :: Python
Classifier: Programming Language :: Python :: 3
Classifier: Programming Language :: Python :: 3.7
Classifier: Programming Language :: Python :: 3.8
Classifier: Programming Language :: Python :: 3.9
Classifier: Programming Language :: Python :: 3.10
Classifier: Programming Language :: Python :: 3.11
Classifier: Programming Language :: Python :: 3
Classifier: Topic :: Security
Requires-Dist: cachetools (>=5.0.0)
Requires-Dist: django (>=2.2)
Requires-Dist: djangorestframework (>=3.0)
Requires-Dist: dry-rest-permissions (>=0.1)
Requires-Dist: python-keycloak (>=2.6.0)
Project-URL: Repository, https://github.com/urbanplatform/django-keycloak-auth
